{
  "users": [
    {
      "username": "a",
      "email": "a@a.com",
      "gender": "male",
      "id": 1
    },
    {
      "username": "b",
      "email": "b@b.com",
      "gender": "male",
      "id": 2
    },
    {
      "username": "c",
      "email": "c@c.com",
      "gender": "female",
      "id": 3
    },
    {
      "username": "d",
      "email": "d@d.com",
      "gender": "male",
      "id": 4
    },
    {
      "username": "e",
      "email": "e@e.com",
      "gender": "female",
      "id": 5
    },
    {
      "username": "f",
      "email": "f@f.com",
      "gender": "male",
      "id": 6
    },
    {
      "username": "g",
      "email": "g@g.com",
      "gender": "female",
      "id": 7
    },
    {
      "username": "h",
      "email": "h@h.com",
      "gender": "female",
      "id": 8
    },
    {
      "username": "i",
      "email": "i@i.com",
      "gender": "male",
      "id": 9
    },
    {
      "username": "j",
      "email": "j@j.com",
      "gender": "male",
      "id": 10
    },
    {
      "username": "k",
      "email": "k@k.com",
      "gender": "female",
      "id": 11
    }
  ]
}